pydantic_django_utils/__init__.py
pydantic_django_utils/drf_errors.py
pydantic_django_utils/openapi.py
pydantic_django_utils/pydantic_querydict.py
pydantic_django_utils-0.0.1.dist-info/LICENSE
pydantic_django_utils-0.0.1.dist-info/METADATA
pydantic_django_utils-0.0.1.dist-info/WHEEL
pydantic_django_utils-0.0.1.dist-info/top_level.txt
pydantic_django_utils-0.0.1.dist-info/RECORD
