Metadata-Version: 2.1
Name: pydantic-django-utils
Version: 0.0.1
Summary: Utils to help integrate pydantic into Django projects
Home-page: https://gitlab.com/matthewhughes/pydantic-django-utils
Author: Matthew Hughes
Author-email: matthewhughes934@gmail.com
License: UNKNOWN
Platform: UNKNOWN
Classifier: Programming Language :: Python :: 3
Classifier: Programming Language :: Python :: 3.6
Classifier: Programming Language :: Python :: 3.7
Classifier: Programming Language :: Python :: 3.8
Classifier: Programming Language :: Python :: 3.9
Classifier: License :: OSI Approved :: MIT License
Classifier: Operating System :: OS Independent
Requires-Python: >=3.6
License-File: LICENSE
Requires-Dist: pydantic
Requires-Dist: django
Requires-Dist: typing-extensions (>=3.7.4.3)
